ffmpeg_editlist.py
ffmpeg_editlist-0.5.5.dist-info/entry_points.txt
ffmpeg_editlist-0.5.5.dist-info/licenses/LICENSE
ffmpeg_editlist-0.5.5.dist-info/WHEEL
ffmpeg_editlist-0.5.5.dist-info/METADATA
ffmpeg_editlist-0.5.5.dist-info/RECORD
