Metadata-Version: 2.4
Name: ffmpeg-editlist
Version: 0.5.5
Summary: Cut and splice video files using a YAML definition file and ffmpeg
Author: Richard Darst
Classifier: License :: OSI Approved :: MIT License
License-File: LICENSE
Requires-Dist: pyyaml
Requires-Dist: srt ; extra == "srt"
Requires-Dist: pytest ; extra == "test"
Project-URL: Home, https://github.com/coderefinery/ffmpeg-editlist/
Provides-Extra: srt
Provides-Extra: test
